Metadata-Version: 1.0
Name: lib-LSM
Version: 0.0.1
Summary: Issue books and calculate fine
Home-page: UNKNOWN
Author: Pushkar Rahane
Author-email: p.rahane210@gmail.com
License: UNKNOWN
Keywords: issue book
Platform: UNKNOWN
